{
  "frames": {
    "background/stage.png": {
      "frame": {
        "x": 2,
        "y": 2,
        "w": 3200,
        "h": 2188
      },
      "rotated": false,
      "trimmed": false,
      "spriteSourceSize": {
        "x": 0,
        "y": 0,
        "w": 3200,
        "h": 2188
      },
      "sourceSize": {
        "w": 3200,
        "h": 2188
      },
      "pivot": {
        "x": 0.5,
        "y": 0.5
      }
    },
    "objects/clock-morning.png": {
      "frame": {
        "x": 3206,
        "y": 2,
        "w": 768,
        "h": 784
      },
      "rotated": true,
      "trimmed": false,
      "spriteSourceSize": {
        "x": 0,
        "y": 0,
        "w": 768,
        "h": 784
      },
      "sourceSize": {
        "w": 768,
        "h": 784
      },
      "pivot": {
        "x": 0.5,
        "y": 0.5
      }
    },
    "objects/clock-night.png": {
      "frame": {
        "x": 3206,
        "y": 774,
        "w": 768,
        "h": 784
      },
      "rotated": true,
      "trimmed": false,
      "spriteSourceSize": {
        "x": 0,
        "y": 0,
        "w": 768,
        "h": 784
      },
      "sourceSize": {
        "w": 768,
        "h": 784
      },
      "pivot": {
        "x": 0.5,
        "y": 0.5
      }
    },
    "objects/clock-transition1.png": {
      "frame": {
        "x": 3206,
        "y": 1546,
        "w": 768,
        "h": 784
      },
      "rotated": true,
      "trimmed": false,
      "spriteSourceSize": {
        "x": 0,
        "y": 0,
        "w": 768,
        "h": 784
      },
      "sourceSize": {
        "w": 768,
        "h": 784
      },
      "pivot": {
        "x": 0.5,
        "y": 0.5
      }
    },
    "objects/clock-transition2.png": {
      "frame": {
        "x": 2,
        "y": 2318,
        "w": 768,
        "h": 784
      },
      "rotated": false,
      "trimmed": false,
      "spriteSourceSize": {
        "x": 0,
        "y": 0,
        "w": 768,
        "h": 784
      },
      "sourceSize": {
        "w": 768,
        "h": 784
      },
      "pivot": {
        "x": 0.5,
        "y": 0.5
      }
    },
    "fx/fire.png": {
      "frame": {
        "x": 2,
        "y": 2194,
        "w": 108,
        "h": 50
      },
      "rotated": true,
      "trimmed": true,
      "spriteSourceSize": {
        "x": 150,
        "y": 1,
        "w": 108,
        "h": 50
      },
      "sourceSize": {
        "w": 258,
        "h": 51
      },
      "pivot": {
        "x": 0.5,
        "y": 0.5
      }
    },
    "objects/amplifier.png": {
      "frame": {
        "x": 56,
        "y": 2194,
        "w": 101,
        "h": 128
      },
      "rotated": true,
      "trimmed": false,
      "spriteSourceSize": {
        "x": 0,
        "y": 0,
        "w": 101,
        "h": 128
      },
      "sourceSize": {
        "w": 101,
        "h": 128
      },
      "pivot": {
        "x": 0.5,
        "y": 0.5
      }
    },
    "objects/guitar.png": {
      "frame": {
        "x": 188,
        "y": 2194,
        "w": 96,
        "h": 301
      },
      "rotated": true,
      "trimmed": false,
      "spriteSourceSize": {
        "x": 0,
        "y": 0,
        "w": 96,
        "h": 301
      },
      "sourceSize": {
        "w": 96,
        "h": 301
      },
      "pivot": {
        "x": 0.5,
        "y": 0.5
      }
    },
    "fx/particle.png": {
      "frame": {
        "x": 493,
        "y": 2194,
        "w": 44,
        "h": 44
      },
      "rotated": false,
      "trimmed": false,
      "spriteSourceSize": {
        "x": 0,
        "y": 0,
        "w": 44,
        "h": 44
      },
      "sourceSize": {
        "w": 44,
        "h": 44
      },
      "pivot": {
        "x": 0.5,
        "y": 0.5
      }
    },
    "background/room-night.jpg": {
      "frame": {
        "x": 2,
        "y": 3106,
        "w": 768,
        "h": 512
      },
      "rotated": true,
      "trimmed": false,
      "spriteSourceSize": {
        "x": 0,
        "y": 0,
        "w": 768,
        "h": 512
      },
      "sourceSize": {
        "w": 768,
        "h": 512
      },
      "pivot": {
        "x": 0.5,
        "y": 0.5
      }
    },
    "background/room.jpeg": {
      "frame": {
        "x": 518,
        "y": 3106,
        "w": 768,
        "h": 512
      },
      "rotated": true,
      "trimmed": false,
      "spriteSourceSize": {
        "x": 0,
        "y": 0,
        "w": 768,
        "h": 512
      },
      "sourceSize": {
        "w": 768,
        "h": 512
      },
      "pivot": {
        "x": 0.5,
        "y": 0.5
      }
    },
    "fx/notes2.png": {
      "frame": {
        "x": 774,
        "y": 2318,
        "w": 465,
        "h": 751
      },
      "rotated": false,
      "trimmed": false,
      "spriteSourceSize": {
        "x": 0,
        "y": 0,
        "w": 465,
        "h": 751
      },
      "sourceSize": {
        "w": 465,
        "h": 751
      },
      "pivot": {
        "x": 0.5,
        "y": 0.5
      }
    },
    "fx/notes1.png": {
      "frame": {
        "x": 1034,
        "y": 3073,
        "w": 422,
        "h": 687
      },
      "rotated": false,
      "trimmed": false,
      "spriteSourceSize": {
        "x": 0,
        "y": 0,
        "w": 422,
        "h": 687
      },
      "sourceSize": {
        "w": 422,
        "h": 687
      },
      "pivot": {
        "x": 0.5,
        "y": 0.5
      }
    },
    "ui/ui-player.png": {
      "frame": {
        "x": 1034,
        "y": 3764,
        "w": 162,
        "h": 270
      },
      "rotated": true,
      "trimmed": false,
      "spriteSourceSize": {
        "x": 0,
        "y": 0,
        "w": 162,
        "h": 270
      },
      "sourceSize": {
        "w": 162,
        "h": 270
      },
      "pivot": {
        "x": 0.5,
        "y": 0.5
      }
    },
    "character/buck-hd-ec-s.png": {
      "frame": {
        "x": 1243,
        "y": 2318,
        "w": 352,
        "h": 594
      },
      "rotated": false,
      "trimmed": false,
      "spriteSourceSize": {
        "x": 0,
        "y": 0,
        "w": 352,
        "h": 594
      },
      "sourceSize": {
        "w": 352,
        "h": 594
      },
      "pivot": {
        "x": 0.5,
        "y": 0.5
      }
    },
    "character/buck-hd-ec.png": {
      "frame": {
        "x": 1460,
        "y": 2916,
        "w": 352,
        "h": 594
      },
      "rotated": false,
      "trimmed": false,
      "spriteSourceSize": {
        "x": 0,
        "y": 0,
        "w": 352,
        "h": 594
      },
      "sourceSize": {
        "w": 352,
        "h": 594
      },
      "pivot": {
        "x": 0.5,
        "y": 0.5
      }
    },
    "character/buck-hd-eh-s.png": {
      "frame": {
        "x": 1599,
        "y": 2318,
        "w": 352,
        "h": 594
      },
      "rotated": false,
      "trimmed": false,
      "spriteSourceSize": {
        "x": 0,
        "y": 0,
        "w": 352,
        "h": 594
      },
      "sourceSize": {
        "w": 352,
        "h": 594
      },
      "pivot": {
        "x": 0.5,
        "y": 0.5
      }
    },
    "ui/radio-off.png": {
      "frame": {
        "x": 1460,
        "y": 3514,
        "w": 444,
        "h": 324
      },
      "rotated": true,
      "trimmed": false,
      "spriteSourceSize": {
        "x": 0,
        "y": 0,
        "w": 444,
        "h": 324
      },
      "sourceSize": {
        "w": 444,
        "h": 324
      },
      "pivot": {
        "x": 0.5,
        "y": 0.5
      }
    },
    "ui/radio.png": {
      "frame": {
        "x": 1788,
        "y": 3514,
        "w": 444,
        "h": 324
      },
      "rotated": true,
      "trimmed": false,
      "spriteSourceSize": {
        "x": 0,
        "y": 0,
        "w": 444,
        "h": 324
      },
      "sourceSize": {
        "w": 444,
        "h": 324
      },
      "pivot": {
        "x": 0.5,
        "y": 0.5
      }
    },
    "character/buck-hd-eh.png": {
      "frame": {
        "x": 1816,
        "y": 2916,
        "w": 352,
        "h": 594
      },
      "rotated": false,
      "trimmed": false,
      "spriteSourceSize": {
        "x": 0,
        "y": 0,
        "w": 352,
        "h": 594
      },
      "sourceSize": {
        "w": 352,
        "h": 594
      },
      "pivot": {
        "x": 0.5,
        "y": 0.5
      }
    },
    "character/buck-hd-eo.png": {
      "frame": {
        "x": 2116,
        "y": 2318,
        "w": 352,
        "h": 594
      },
      "rotated": false,
      "trimmed": false,
      "spriteSourceSize": {
        "x": 0,
        "y": 0,
        "w": 352,
        "h": 594
      },
      "sourceSize": {
        "w": 352,
        "h": 594
      },
      "pivot": {
        "x": 0.5,
        "y": 0.5
      }
    },
    "character/buck-hd-ey-s.png": {
      "frame": {
        "x": 2472,
        "y": 2318,
        "w": 352,
        "h": 594
      },
      "rotated": false,
      "trimmed": false,
      "spriteSourceSize": {
        "x": 0,
        "y": 0,
        "w": 352,
        "h": 594
      },
      "sourceSize": {
        "w": 352,
        "h": 594
      },
      "pivot": {
        "x": 0.5,
        "y": 0.5
      }
    },
    "character/buck-hu-ec-s.png": {
      "frame": {
        "x": 2828,
        "y": 2194,
        "w": 352,
        "h": 594
      },
      "rotated": false,
      "trimmed": false,
      "spriteSourceSize": {
        "x": 0,
        "y": 0,
        "w": 352,
        "h": 594
      },
      "sourceSize": {
        "w": 352,
        "h": 594
      },
      "pivot": {
        "x": 0.5,
        "y": 0.5
      }
    },
    "character/buck-hu-ec.png": {
      "frame": {
        "x": 2828,
        "y": 2792,
        "w": 352,
        "h": 594
      },
      "rotated": false,
      "trimmed": false,
      "spriteSourceSize": {
        "x": 0,
        "y": 0,
        "w": 352,
        "h": 594
      },
      "sourceSize": {
        "w": 352,
        "h": 594
      },
      "pivot": {
        "x": 0.5,
        "y": 0.5
      }
    },
    "character/buck-hu-eh-s.png": {
      "frame": {
        "x": 2828,
        "y": 3390,
        "w": 352,
        "h": 594
      },
      "rotated": false,
      "trimmed": false,
      "spriteSourceSize": {
        "x": 0,
        "y": 0,
        "w": 352,
        "h": 594
      },
      "sourceSize": {
        "w": 352,
        "h": 594
      },
      "pivot": {
        "x": 0.5,
        "y": 0.5
      }
    },
    "character/buck-hu-eh.png": {
      "frame": {
        "x": 2172,
        "y": 2916,
        "w": 352,
        "h": 594
      },
      "rotated": true,
      "trimmed": false,
      "spriteSourceSize": {
        "x": 0,
        "y": 0,
        "w": 352,
        "h": 594
      },
      "sourceSize": {
        "w": 352,
        "h": 594
      },
      "pivot": {
        "x": 0.5,
        "y": 0.5
      }
    },
    "character/buck-hu-eo-s.png": {
      "frame": {
        "x": 2172,
        "y": 3272,
        "w": 352,
        "h": 594
      },
      "rotated": true,
      "trimmed": false,
      "spriteSourceSize": {
        "x": 0,
        "y": 0,
        "w": 352,
        "h": 594
      },
      "sourceSize": {
        "w": 352,
        "h": 594
      },
      "pivot": {
        "x": 0.5,
        "y": 0.5
      }
    },
    "character/buck-hu-eo.png": {
      "frame": {
        "x": 2116,
        "y": 3628,
        "w": 352,
        "h": 594
      },
      "rotated": true,
      "trimmed": false,
      "spriteSourceSize": {
        "x": 0,
        "y": 0,
        "w": 352,
        "h": 594
      },
      "sourceSize": {
        "w": 352,
        "h": 594
      },
      "pivot": {
        "x": 0.5,
        "y": 0.5
      }
    },
    "objects/switch-off.png": {
      "frame": {
        "x": 3184,
        "y": 2318,
        "w": 346,
        "h": 552
      },
      "rotated": true,
      "trimmed": false,
      "spriteSourceSize": {
        "x": 0,
        "y": 0,
        "w": 346,
        "h": 552
      },
      "sourceSize": {
        "w": 346,
        "h": 552
      },
      "pivot": {
        "x": 0.5,
        "y": 0.5
      }
    },
    "objects/switch-on.png": {
      "frame": {
        "x": 3184,
        "y": 2668,
        "w": 346,
        "h": 552
      },
      "rotated": true,
      "trimmed": false,
      "spriteSourceSize": {
        "x": 0,
        "y": 0,
        "w": 346,
        "h": 552
      },
      "sourceSize": {
        "w": 346,
        "h": 552
      },
      "pivot": {
        "x": 0.5,
        "y": 0.5
      }
    }
  },
  "meta": {
    "app": "http://free-tex-packer.com",
    "version": "0.6.7",
    "image": "textures.png",
    "format": "RGBA8888",
    "size": {
      "w": 3992,
      "h": 3986
    },
    "scale": 1
  }
}